LICENSE
MANIFEST.in
README.md
setup.py
sklearn_pmml/__init__.py
sklearn_pmml/pmml.py
sklearn_pmml.egg-info/PKG-INFO
sklearn_pmml.egg-info/SOURCES.txt
sklearn_pmml.egg-info/dependency_links.txt
sklearn_pmml.egg-info/requires.txt
sklearn_pmml.egg-info/top_level.txt
sklearn_pmml/convert/__init__.py
sklearn_pmml/convert/features.py
sklearn_pmml/convert/gbrt.py
sklearn_pmml/convert/model.py
sklearn_pmml/convert/random_forest.py
sklearn_pmml/convert/tree.py
sklearn_pmml/convert/utils.py
sklearn_pmml/convert/test/__init__.py
sklearn_pmml/convert/test/test_decisionTreeClassifierConverter.py
sklearn_pmml/convert/test/test_derived_fields.py
sklearn_pmml/convert/test/test_gradientBoostingConverter.py