Metadata-Version: 1.0
Name: sklearn-pmml
Version: 0.1.1
Summary: A library that allows serialization of SciKit-Learn estimators into PMML
Home-page: https://github.com/alex-pirozhenko/sklearn-pmml
Author: Alex Pirozhenko
Author-email: apirozhenko@pulsepoint.com
License: MIT
Platform: UNKNOWN
